{
  "$schema": "http://json-schema.org/draft-07/schema#",
  "$id": "/schemas/core/pagination-response.json",
  "title": "Pagination Response",
  "description": "Standard cursor-based pagination metadata for list responses",
  "type": "object",
  "properties": {
    "adcp_version": {
      "type": "string",
      "description": "Release-precision AdCP version this party is operating at (VERSION.RELEASE, e.g. \"3.0\", \"3.1\", \"3.1-beta\"). On a request: the buyer's release pin — the seller validates against its supported_versions and returns VERSION_UNSUPPORTED on cross-major mismatch, or downshifts to the highest supported release within the same major. On a response: the release the seller actually served — clients SHOULD validate the response against that release's schema, not against their pin. Patches are not negotiated; surface them as build_version on capabilities for operational visibility. When omitted, falls back to adcp_major_version (deprecated) or server default.",
      "pattern": "^\\d+\\.\\d+(-[a-zA-Z0-9.-]+)?$",
      "examples": [
        "3.0",
        "3.1",
        "3.1-beta",
        "3.1-rc.1"
      ]
    },
    "has_more": {
      "type": "boolean",
      "description": "Whether more results are available beyond this page"
    },
    "cursor": {
      "type": "string",
      "description": "Opaque cursor to pass in the next request to fetch the next page. Only present when has_more is true."
    },
    "total_count": {
      "type": "integer",
      "minimum": 0,
      "description": "Total number of items matching the query across all pages. Optional because not all backends can efficiently compute this."
    }
  },
  "required": [
    "has_more"
  ],
  "additionalProperties": false
}
